{
  "theme": {
    "radius": {
      "borderRadius": {
        "value": "25",
        "type": "borderRadius"
      }
    },
    "background-color": {
      "background": {
        "value": "#c81a6b",
        "type": "color"
      }
    },
    "boxShadow": {
      "default": {
        "value": [
          {
            "x": "8",
            "y": "8",
            "spread": "3",
            "color": "rgba(#4f589c, 0.15)",
            "blur": "4",
            "type": "dropShadow"
          },
          {
            "x": "8",
            "y": "8",
            "spread": "6",
            "color": "#00000033",
            "blur": "5",
            "type": "innerShadow"
          }
        ],
        "type": "boxShadow"
      }
    },
    "button font size": {
      "value": "20px",
      "type": "fontSizes"
    },
    "width": {
      "value": "150px",
      "type": "sizing"
    }
  },
  "$themes": [],
  "$metadata": {
    "tokenSetOrder": [
      "theme"
    ]
  }
}